seestar_mcp/__init__.py
seestar_mcp/__main__.py
seestar_mcp/location_manager.py
seestar_mcp/models.py
seestar_mcp/server.py
seestar_mcp/target_resolver.py
seestar_mcp/telescope_client.py
seestar_mcp-0.1.0.dist-info/METADATA
seestar_mcp-0.1.0.dist-info/WHEEL
seestar_mcp-0.1.0.dist-info/entry_points.txt
seestar_mcp-0.1.0.dist-info/licenses/LICENSE
seestar_mcp-0.1.0.dist-info/RECORD
